toolrunner/__init__.py
toolrunner/core.py
toolrunner-1.0.0.dist-info/LICENSE
toolrunner-1.0.0.dist-info/METADATA
toolrunner-1.0.0.dist-info/WHEEL
toolrunner-1.0.0.dist-info/top_level.txt
toolrunner-1.0.0.dist-info/RECORD
