Metadata-Version: 2.1
Name: toolrunner
Version: 1.0.0
Summary: Quick tool automation
Home-page: https://github.com/LLCZ00/Toolrunner
Author: LLCZ00
License: Apache 2.0
Keywords: malware analysis automation
Classifier: Development Status :: 5 - Production/Stable
Classifier: Intended Audience :: Information Technology
Classifier: Intended Audience :: Developers
Classifier: License :: OSI Approved :: Apache Software License
Classifier: Natural Language :: English
Classifier: Programming Language :: Python :: 3
Classifier: Operating System :: OS Independent
Classifier: Topic :: Utilities
Requires-Python: >=3.9
License-File: LICENSE
